mdx_to_pd/__init__.py
mdx_to_pd/mdx_to_pd.py
mdx_to_pd-0.0.6.dist-info/METADATA
mdx_to_pd-0.0.6.dist-info/WHEEL
mdx_to_pd-0.0.6.dist-info/licence.txt
mdx_to_pd-0.0.6.dist-info/top_level.txt
mdx_to_pd-0.0.6.dist-info/RECORD
