Metadata-Version: 2.1
Name: mdx-to-pd
Version: 0.0.6
Summary: MDX query reader from Microsoft Analytics Services OLAP returning pandas DataFrame
Author: Peter Kazmir
Classifier: Programming Language :: Python :: 3
Classifier: License :: OSI Approved :: MIT License
Classifier: Operating System :: Microsoft :: Windows :: Windows 10
Requires-Python: >=3.10
License-File: licence.txt
